{
  "_type": "export",
  "__export_format": 4,
  "__export_date": "2024-07-19T18:01:04.401Z",
  "__export_source": "insomnia.desktop.app:v9.3.2",
  "resources": [
    {
      "_id": "req_dd53cfe9a37d48cea6db3e7e538b77ca",
      "parentId": "wrk_8286f52d894f4dd0ac8e7886d4883e85",
      "modified": 1721345061215,
      "created": 1721254960129,
      "url": "http://localhost:8080/api/transacoes/pagamento",
      "name": "Realizar um Pagamento",
      "description": "",
      "method": "POST",
      "body": {
        "mimeType": "application/json",
        "text": " {\n        \"transacao\": {\n            \"cartao\": \"4444**********1234\",\n            \"id\": \"1000235689001\",\n            \"descricao\": {\n                \"valor\": \"500.50\",\n                \"dataHora\": \"01/05/2021 18:30:00\",\n                \"estabelecimento\": \"Loja 1\"\n            },\n            \"formaPagamento\": {\n                \"tipo\": \"PARCELADO_EMISSOR\",\n                \"parcelas\": \"1\"\n            }\n        }\n}"
      },
      "parameters": [],
      "headers": [
        {
          "name": "Content-Type",
          "value": "application/json"
        },
        {
          "name": "User-Agent",
          "value": "insomnia/9.3.2"
        }
      ],
      "authentication": {},
      "metaSortKey": -1721254960129,
      "isPrivate": false,
      "pathParameters": [],
      "settingStoreCookies": true,
      "settingSendCookies": true,
      "settingDisableRenderRequestBody": false,
      "settingEncodeUrl": true,
      "settingRebuildPath": true,
      "settingFollowRedirects": "global",
      "_type": "request"
    },
    {
      "_id": "wrk_8286f52d894f4dd0ac8e7886d4883e85",
      "parentId": null,
      "modified": 1721254882757,
      "created": 1721254882757,
      "name": "desafio java",
      "description": "",
      "scope": "collection",
      "_type": "workspace"
    },
    {
      "_id": "req_0c738245d7be43288f2d4fe750b4ec6d",
      "parentId": "wrk_8286f52d894f4dd0ac8e7886d4883e85",
      "modified": 1721255053269,
      "created": 1721254888247,
      "url": "http://localhost:8080/api/transacoes",
      "name": "Consultar Todas as Transações",
      "description": "",
      "method": "GET",
      "body": {},
      "parameters": [],
      "headers": [
        {
          "name": "User-Agent",
          "value": "insomnia/9.3.2"
        }
      ],
      "authentication": {},
      "metaSortKey": -1721254888247,
      "isPrivate": false,
      "pathParameters": [],
      "settingStoreCookies": true,
      "settingSendCookies": true,
      "settingDisableRenderRequestBody": false,
      "settingEncodeUrl": true,
      "settingRebuildPath": true,
      "settingFollowRedirects": "global",
      "_type": "request"
    },
    {
      "_id": "req_9dcafae23f2a4818aab1680fdd7acf76",
      "parentId": "wrk_8286f52d894f4dd0ac8e7886d4883e85",
      "modified": 1721324218376,
      "created": 1721255067891,
      "url": "http://localhost:8080/api/transacoes/100023568900001",
      "name": "Consultar Transação",
      "description": "",
      "method": "GET",
      "body": {},
      "parameters": [],
      "headers": [
        {
          "name": "User-Agent",
          "value": "insomnia/9.3.2"
        }
      ],
      "authentication": {},
      "metaSortKey": -1720862963777,
      "isPrivate": false,
      "pathParameters": [],
      "settingStoreCookies": true,
      "settingSendCookies": true,
      "settingDisableRenderRequestBody": false,
      "settingEncodeUrl": true,
      "settingRebuildPath": true,
      "settingFollowRedirects": "global",
      "_type": "request"
    },
    {
      "_id": "req_33b00bed63c64d9da852decfe7d3d67f",
      "parentId": "wrk_8286f52d894f4dd0ac8e7886d4883e85",
      "modified": 1721319102993,
      "created": 1721318791770,
      "url": "http://localhost:8080/api/transacoes/estorno/100023568900001",
      "name": "extornar Transação",
      "description": "",
      "method": "GET",
      "body": {},
      "parameters": [],
      "headers": [
        {
          "name": "User-Agent",
          "value": "insomnia/9.3.2"
        }
      ],
      "authentication": {},
      "metaSortKey": -1720667001542,
      "isPrivate": false,
      "pathParameters": [],
      "settingStoreCookies": true,
      "settingSendCookies": true,
      "settingDisableRenderRequestBody": false,
      "settingEncodeUrl": true,
      "settingRebuildPath": true,
      "settingFollowRedirects": "global",
      "_type": "request"
    },
    {
      "_id": "env_f8db9e52b0dd85fb35aa87a89ab1e18b63cce233",
      "parentId": "wrk_8286f52d894f4dd0ac8e7886d4883e85",
      "modified": 1721254882760,
      "created": 1721254882760,
      "name": "Base Environment",
      "data": {},
      "dataPropertyOrder": null,
      "color": null,
      "isPrivate": false,
      "metaSortKey": 1721254882760,
      "_type": "environment"
    },
    {
      "_id": "jar_f8db9e52b0dd85fb35aa87a89ab1e18b63cce233",
      "parentId": "wrk_8286f52d894f4dd0ac8e7886d4883e85",
      "modified": 1721254882761,
      "created": 1721254882761,
      "name": "Default Jar",
      "cookies": [],
      "_type": "cookie_jar"
    }
  ]
}